AUTHORS.txt
LICENSE.txt
README.md
boilergen.py
docxtool.py
setup.cfg
setup.py
boiler_templates/dtpt-1.md
document_reporter/__init__.py
document_reporter.egg-info/PKG-INFO
document_reporter.egg-info/SOURCES.txt
document_reporter.egg-info/dependency_links.txt
document_reporter.egg-info/not-zip-safe
document_reporter.egg-info/requires.txt
document_reporter.egg-info/top_level.txt
document_reporter/boilers/__init__.py
document_reporter/boilers/kvsub.py
document_reporter/boilers/vapt.py
document_reporter/md/__init__.py
document_reporter/md/documentx.py
document_reporter/md/format_tag.py
document_reporter/utils/__init__.py
document_reporter/utils/docx_helper.py
document_reporter/utils/errx_helper.py
document_reporter/utils/log_helper.py
document_reporter/utils/parsers.py
document_reporter/utils/path_helper.py
document_reporter/utils/vapt_helper.py