Metadata-Version: 2.1
Name: document-reporter
Version: 0.1.1
Summary: a python module to create reports from text-based files (e.g., markdown, xml)
Home-page: https://github.com/toranova/document-reporter/
Author: Chia Jason
Author-email: chia_jason96@live.com
License: AGPL-3.0-or-later
Download-URL: https://github.com/ToraNova/document-reporter/archive/refs/tags/v0.1.1.tar.gz
Keywords: docx,md,xml
Platform: UNKNOWN
Classifier: Development Status :: 3 - Alpha
Classifier: Programming Language :: Python :: 3
Classifier: License :: OSI Approved :: GNU Affero General Public License v3 or later (AGPLv3+)
Classifier: Operating System :: OS Independent
Classifier: Intended Audience :: Developers
License-File: LICENSE.txt
License-File: AUTHORS.txt
